shove_git/__init__.py
shove_git/store.py
shove_git/test/__init__.py
shove_git/test/test_gitstore.py
shove_git-0.1.0.dist-info/DESCRIPTION.rst
shove_git-0.1.0.dist-info/METADATA
shove_git-0.1.0.dist-info/RECORD
shove_git-0.1.0.dist-info/WHEEL
shove_git-0.1.0.dist-info/entry_points.txt
shove_git-0.1.0.dist-info/metadata.json
shove_git-0.1.0.dist-info/pbr.json
shove_git-0.1.0.dist-info/top_level.txt
